se/__init__.py
se/browser.py
se/css.py
se/easy_xml.py
se/epub.py
se/formatting.py
se/images.py
se/main.py
se/se_epub.py
se/se_epub_build.py
se/se_epub_generate_toc.py
se/se_epub_lint.py
se/spelling.py
se/typography.py
se/commands/__init__.py
se/commands/build.py
se/commands/build_images.py
se/commands/clean.py
se/commands/compare_versions.py
se/commands/create_draft.py
se/commands/dec2roman.py
se/commands/extract_ebook.py
se/commands/find_mismatched_diacritics.py
se/commands/help.py
se/commands/hyphenate.py
se/commands/interactive_sr.py
se/commands/lint.py
se/commands/make_url_safe.py
se/commands/modernize_spelling.py
se/commands/prepare_release.py
se/commands/print_manifest.py
se/commands/print_spine.py
se/commands/print_title.py
se/commands/print_toc.py
se/commands/recompose_epub.py
se/commands/renumber_endnotes.py
se/commands/reorder_endnotes.py
se/commands/roman2dec.py
se/commands/semanticate.py
se/commands/split_file.py
se/commands/titlecase.py
se/commands/typogrify.py
se/commands/unicode_names.py
se/commands/version.py
se/commands/word_count.py
se/commands/xpath.py
se/data/__init__.py
se/data/browser.css
se/data/mathmlcontent2presentation.xsl
se/data/navdoc2ncx.xsl
se/data/words
se/data/__pycache__/__init__.cpython-39.pyc
se/data/epubcheck/CHANGELOG.txt
se/data/epubcheck/LICENSE.txt
se/data/epubcheck/README.txt
se/data/epubcheck/THIRD-PARTY.txt
se/data/epubcheck/__init__.py
se/data/epubcheck/epubcheck.jar
se/data/epubcheck/__pycache__/__init__.cpython-39.pyc
se/data/epubcheck/lib/Saxon-HE-9.8.0-8.jar
se/data/epubcheck/lib/animal-sniffer-annotations-1.14.jar
se/data/epubcheck/lib/checker-compat-qual-2.0.0.jar
se/data/epubcheck/lib/common-image-3.4.1.jar
se/data/epubcheck/lib/common-io-3.4.1.jar
se/data/epubcheck/lib/common-lang-3.4.1.jar
se/data/epubcheck/lib/commons-compress-1.20.jar
se/data/epubcheck/lib/error_prone_annotations-2.1.3.jar
se/data/epubcheck/lib/guava-24.1.1-android.jar
se/data/epubcheck/lib/imageio-core-3.4.1.jar
libro_org-0.3.dist-info/LICENSE.md
libro_org-0.3.dist-info/METADATA
libro_org-0.3.dist-info/WHEEL
libro_org-0.3.dist-info/entry_points.txt
libro_org-0.3.dist-info/top_level.txt
libro_org-0.3.dist-info/RECORD
