Metadata-Version: 2.1
Name: libro-org
Version: 0.3
Summary: The toolset used to produce Libro.org epub ebooks.
Home-page: https://libro.org
Author: Libro.org
Author-email: admin@libro.org
License: UNKNOWN
Project-URL: Source, https://github.com/Libro-Org/tools/
Keywords: ebooks epub
Platform: UNKNOWN
Classifier: Development Status :: 3 - Alpha
Classifier: Intended Audience :: Developers
Classifier: Topic :: Software Development :: Build Tools
Classifier: License :: OSI Approved :: GNU General Public License v3 or later (GPLv3+)
Classifier: Programming Language :: Python :: 3
Classifier: Programming Language :: Python :: 3.6
Requires-Python: >=3.6
License-File: LICENSE.md
Requires-Dist: cairosvg (==2.5.2)
Requires-Dist: chardet (==3.0.4)
Requires-Dist: cssselect (==1.1.0)
Requires-Dist: cssutils (==1.0.2)
Requires-Dist: ftfy (==5.8)
Requires-Dist: gitpython (==3.1.11)
Requires-Dist: importlib-resources (==1.0.2)
Requires-Dist: lxml (==4.6.3)
Requires-Dist: natsort (==7.1.0)
Requires-Dist: pillow (==8.1.1)
Requires-Dist: psutil (==5.8.0)
Requires-Dist: pyopenssl (==20.0.0)
Requires-Dist: pyphen (==0.10.0)
Requires-Dist: regex (==2020.11.13)
Requires-Dist: requests (==2.25.0)
Requires-Dist: rich (==9.4.0)
Requires-Dist: roman (==3.3.0)
Requires-Dist: selenium (==3.141.0)
Requires-Dist: smartypants (==2.0.1)
Requires-Dist: tinycss2 (==1.1.0)
Requires-Dist: titlecase (==0.13.0)
Requires-Dist: unidecode (==1.2.0)
